example/__init__.py
vpyn/__init__.py
vpyn/__main__.py
vpyn/cli.py
vpyn/gherkin.py
vpyn/net.py
vpyn/pipeline.py
vpyn-0.1.3.dist-info/METADATA
vpyn-0.1.3.dist-info/WHEEL
vpyn-0.1.3.dist-info/entry_points.txt
vpyn-0.1.3.dist-info/RECORD
