Metadata-Version: 2.1
Name: vpyn
Version: 0.1.3
Summary: Virtual Python Networks
Home-page: https://vpyn.net
Author: Peter Thompson
Author-email: peter.thompson92@gmail.com
Requires-Python: >=3.11,<4.0
Classifier: Programming Language :: Python :: 3
Classifier: Programming Language :: Python :: 3.11
Project-URL: Documentation, https://vpyn.net/docs
Project-URL: Repository, https://github.com/9pt7/vpyn
